parski/__init__.py
parski-0.0.10.46.dist-info/DESCRIPTION.rst
parski-0.0.10.46.dist-info/METADATA
parski-0.0.10.46.dist-info/RECORD
parski-0.0.10.46.dist-info/WHEEL
parski-0.0.10.46.dist-info/metadata.json
parski-0.0.10.46.dist-info/top_level.txt
