Metadata-Version: 2.0
Name: parski
Version: 0.0.10.46
Summary: Helper library for filtering json data
Home-page: https://github.build.ge.com/CloudPod/parski
Author: Russell Endicott
Author-email: rendicott@gmail.com
License: UNKNOWN
Keywords: vpc,json,parski
Platform: UNKNOWN
